{
  "id": "course-1775445452856-6ijb2ebx0",
  "version": 2,
  "name": "ALSCCA-2026-Pts2",
  "cones": [
    {
      "id": "cone-1776904186918-0x9xalal9",
      "x": 233.69837951660156,
      "y": 107.35233306884766,
      "type": "standard"
    },
    {
      "id": "cone-1776904188905-9nt49pg4v",
      "x": 241.89747619628906,
      "y": 97.1275634765625,
      "type": "standard"
    },
    {
      "id": "cone-1776904190239-iaaet4f52",
      "x": 242.66915893554688,
      "y": 95.87358093261719,
      "type": "standard"
    },
    {
      "id": "cone-1776904191170-wpw820wpq",
      "x": 243.4408416748047,
      "y": 94.3302230834961,
      "type": "standard"
    },
    {
      "id": "cone-1776904192332-r6c1rvsw5",
      "x": 244.30899047851562,
      "y": 93.26915740966797,
      "type": "standard"
    },
    {
      "id": "cone-1776904193224-dd32hqv3u",
      "x": 245.75588989257812,
      "y": 94.04084014892578,
      "type": "standard"
    },
    {
      "id": "cone-1776904193960-15d9lbcos",
      "x": 247.1063232421875,
      "y": 95.10189819335938,
      "type": "standard"
    },
    {
      "id": "cone-1776904194837-jslwort6d",
      "x": 248.45677185058594,
      "y": 95.7771224975586,
      "type": "standard"
    },
    {
      "id": "cone-1776904197582-0pxjrt0vt",
      "x": 237.07447814941406,
      "y": 123.17178344726562,
      "type": "standard"
    },
    {
      "id": "cone-1776904200297-64t280hnx",
      "x": 237.1709442138672,
      "y": 124.71514129638672,
      "type": "standard"
    },
    {
      "id": "cone-1776904202099-pv5my19hg",
      "x": 237.26739501953125,
      "y": 126.25850677490234,
      "type": "standard"
    },
    {
      "id": "cone-1776904203080-3itsqsh0s",
      "x": 237.36386108398438,
      "y": 127.80186462402344,
      "type": "standard"
    },
    {
      "id": "cone-1776904204527-4o6ukd620",
      "x": 235.82049560546875,
      "y": 127.99478912353516,
      "type": "standard"
    },
    {
      "id": "cone-1776904205886-92g0zoonv",
      "x": 234.47006225585938,
      "y": 127.99478912353516,
      "type": "standard"
    },
    {
      "id": "cone-1776904207295-137b3c2v7",
      "x": 233.02316284179688,
      "y": 127.99478912353516,
      "type": "standard"
    },
    {
      "id": "cone-1776904214008-mm8h3e4vx",
      "x": 303.9070129394531,
      "y": 104.17017364501953,
      "type": "standard"
    },
    {
      "id": "cone-1776904215208-f2f6lqe2r",
      "x": 325.7802734375,
      "y": 95.79681396484375,
      "type": "standard"
    },
    {
      "id": "cone-1776904216572-awv22erva",
      "x": 343.38140869140625,
      "y": 116.47388458251953,
      "type": "standard"
    },
    {
      "id": "cone-1776904218290-17z823g24",
      "x": 324.92584228515625,
      "y": 134.58767700195312,
      "type": "standard"
    },
    {
      "id": "cone-1776904225745-t6t528d9s",
      "x": 239.4833984375,
      "y": 110.49291229248047,
      "type": "pointer",
      "rotation": 35
    },
    {
      "id": "cone-1776904227396-npk9uexdl",
      "x": 228.03411865234375,
      "y": 121.60043334960938,
      "type": "pointer",
      "rotation": 212
    },
    {
      "id": "cone-1776904229623-0qy3j6rli",
      "x": 246.6605682373047,
      "y": 100.58158874511719,
      "type": "pointer",
      "rotation": 94
    },
    {
      "id": "cone-1776904232150-kr8favzsy",
      "x": 265.1161193847656,
      "y": 128.77760314941406,
      "type": "pointer",
      "rotation": 81
    },
    {
      "id": "cone-1776904233771-ryhxtd8d5",
      "x": 253.15419006347656,
      "y": 136.6383056640625,
      "type": "pointer",
      "rotation": 34
    },
    {
      "id": "cone-1776904235331-ix9qni7os",
      "x": 238.6289825439453,
      "y": 154.75210571289062,
      "type": "pointer",
      "rotation": 207
    },
    {
      "id": "cone-1776904237671-t32wds4dx",
      "x": 232.13534545898438,
      "y": 168.59378051757812,
      "type": "pointer",
      "rotation": 66
    },
    {
      "id": "cone-1776904252483-fark97hwz",
      "x": 296.0462951660156,
      "y": 124.84724426269531,
      "type": "pointer",
      "rotation": 90
    },
    {
      "id": "cone-1776904253848-awr5masee",
      "x": 309.8879699707031,
      "y": 127.75228881835938,
      "type": "pointer",
      "rotation": 90
    },
    {
      "id": "cone-1776904255596-t8ytrc5p3",
      "x": 325.2676086425781,
      "y": 125.5307846069336,
      "type": "pointer",
      "rotation": 267
    },
    {
      "id": "cone-1776904256803-jsrtsolg4",
      "x": 334.4953918457031,
      "y": 115.44857788085938,
      "type": "pointer",
      "rotation": 184
    },
    {
      "id": "cone-1776904258146-ptm7u6xpa",
      "x": 325.609375,
      "y": 104.85371398925781,
      "type": "pointer",
      "rotation": 106
    },
    {
      "id": "cone-1776904259564-m8crtwb8r",
      "x": 303.7361145019531,
      "y": 94.94239044189453,
      "type": "pointer",
      "rotation": 257
    },
    {
      "id": "cone-1776904272673-oa5cggwa2",
      "x": 262.9964294433594,
      "y": 101.33848571777344,
      "type": "pointer",
      "rotation": 269
    },
    {
      "id": "cone-1776904272673-wqnuac8mc",
      "x": 262.9666633605957,
      "y": 99.31461971282958,
      "type": "pointer",
      "rotation": 269
    },
    {
      "id": "cone-1776904272673-ngzee9o5s",
      "x": 262.93689727783203,
      "y": 97.29075370788574,
      "type": "pointer",
      "rotation": 269
    },
    {
      "id": "cone-1776904272674-q2ghowi8l",
      "x": 262.90713119506836,
      "y": 95.26688770294189,
      "type": "pointer",
      "rotation": 269
    },
    {
      "id": "cone-1776904280212-b83f18vrv",
      "x": 281.904541015625,
      "y": 97.83699035644531,
      "type": "pointer",
      "rotation": 88
    },
    {
      "id": "cone-1776904280212-uvlblav3e",
      "x": 281.97340255737305,
      "y": 100.35048389434814,
      "type": "pointer",
      "rotation": 88
    },
    {
      "id": "cone-1776904280212-trchcicrd",
      "x": 282.0422640991211,
      "y": 102.86397743225098,
      "type": "pointer",
      "rotation": 88
    },
    {
      "id": "cone-1776904280212-4gess3kan",
      "x": 282.11112564086915,
      "y": 105.37747097015381,
      "type": "pointer",
      "rotation": 88
    },
    {
      "id": "cone-1776904289206-wa63dimxt",
      "x": 281.0875244140625,
      "y": 130.16751098632812,
      "type": "pointer",
      "rotation": 262
    },
    {
      "id": "cone-1776904289206-bwmcumoge",
      "x": 280.7432077026367,
      "y": 127.68844821929932,
      "type": "pointer",
      "rotation": 262
    },
    {
      "id": "cone-1776904289206-fhuixz53u",
      "x": 280.3988909912109,
      "y": 125.20938545227051,
      "type": "pointer",
      "rotation": 262
    },
    {
      "id": "cone-1776904289206-pt5lthsvn",
      "x": 280.05457427978513,
      "y": 122.73032268524169,
      "type": "pointer",
      "rotation": 262
    },
    {
      "id": "cone-1776904302248-6ehyubmvy",
      "x": 257.2773132324219,
      "y": 123.74809265136719,
      "type": "pointer",
      "rotation": 325
    },
    {
      "id": "cone-1776904302248-qkuahjv4j",
      "x": 254.80126770555972,
      "y": 125.48860357445479,
      "type": "pointer",
      "rotation": 324
    },
    {
      "id": "cone-1776904302248-zg9cbnu9a",
      "x": 252.42455762420656,
      "y": 127.34046542300416,
      "type": "pointer",
      "rotation": 318
    },
    {
      "id": "cone-1776904302248-13332eex2",
      "x": 250.31592288568115,
      "y": 129.47639246600724,
      "type": "pointer",
      "rotation": 311
    },
    {
      "id": "cone-1776904302248-w7gclkye1",
      "x": 248.51088890130615,
      "y": 131.89735057281115,
      "type": "pointer",
      "rotation": 302
    },
    {
      "id": "cone-1776904302248-0rfgub9g5",
      "x": 247.22770213572025,
      "y": 134.63735359369326,
      "type": "pointer",
      "rotation": 291
    },
    {
      "id": "cone-1776904302248-3hxx3te1x",
      "x": 246.2489880371094,
      "y": 137.48984838867187,
      "type": "pointer",
      "rotation": 288
    },
    {
      "id": "cone-1776904310048-t62c5ayr8",
      "x": 252.49192810058594,
      "y": 153.1606903076172,
      "type": "pointer",
      "rotation": 299
    },
    {
      "id": "cone-1776904310048-imua53ybb",
      "x": 251.01108169555664,
      "y": 155.80141067504883,
      "type": "pointer",
      "rotation": 300
    },
    {
      "id": "cone-1776904310048-io1tvesbp",
      "x": 249.39057530155947,
      "y": 158.32437001676942,
      "type": "pointer",
      "rotation": 307
    },
    {
      "id": "cone-1776904310048-9v7ssultf",
      "x": 247.3411575822878,
      "y": 160.52849809293843,
      "type": "pointer",
      "rotation": 318
    },
    {
      "id": "cone-1776904310048-7krf76ko6",
      "x": 245.03450276936053,
      "y": 162.4930567897768,
      "type": "pointer",
      "rotation": 321
    },
    {
      "id": "cone-1776904310048-1l08mfbfa",
      "x": 242.68816287250044,
      "y": 164.38213456521893,
      "type": "pointer",
      "rotation": 320
    },
    {
      "id": "cone-1776904333860-bogse86na",
      "x": 285.76605224609375,
      "y": 143.94007873535156,
      "type": "standard"
    },
    {
      "id": "cone-1776904333860-mo768jcg8",
      "x": 288.1960464341888,
      "y": 143.33587623075863,
      "type": "standard"
    },
    {
      "id": "cone-1776904333860-m8staldnv",
      "x": 290.6466134523945,
      "y": 142.82787656583977,
      "type": "standard"
    },
    {
      "id": "cone-1776904333860-dcmr4vqdx",
      "x": 293.14790625248713,
      "y": 142.58407795475003,
      "type": "standard"
    },
    {
      "id": "cone-1776904333860-g9hv5zyu6",
      "x": 295.6587770841827,
      "y": 142.4743193722153,
      "type": "standard"
    },
    {
      "id": "cone-1776904344548-22xt9cwwp",
      "x": 331.1688232421875,
      "y": 136.93707275390625,
      "type": "standard"
    },
    {
      "id": "cone-1776904344548-ciedfg7gf",
      "x": 332.6373844525814,
      "y": 137.27976545846462,
      "type": "standard"
    },
    {
      "id": "cone-1776904344548-dvb4vcn6a",
      "x": 334.1243369393712,
      "y": 137.52116158728887,
      "type": "standard"
    },
    {
      "id": "cone-1776904344548-fyixwly9h",
      "x": 335.6168579579429,
      "y": 137.3834675894213,
      "type": "standard"
    },
    {
      "id": "cone-1776904344548-q8qzhk6mu",
      "x": 337.0111813182869,
      "y": 136.84133563416958,
      "type": "standard"
    },
    {
      "id": "cone-1776904344548-t1mhh6i99",
      "x": 337.9958489548931,
      "y": 135.73026223577978,
      "type": "standard"
    },
    {
      "id": "cone-1776904344548-gitr6nk3c",
      "x": 338.5596251894532,
      "y": 134.32276941406252,
      "type": "standard"
    },
    {
      "id": "cone-1776904344548-chh1qo8k8",
      "x": 339.01230072346493,
      "y": 132.88051584316253,
      "type": "standard"
    },
    {
      "id": "cone-1776904359654-k2p0739fj",
      "x": 337.1213684082031,
      "y": 97.13668823242188,
      "type": "standard"
    },
    {
      "id": "cone-1776904359654-ju5qlhlgf",
      "x": 338.63439750671387,
      "y": 97.22422504425049,
      "type": "standard"
    },
    {
      "id": "cone-1776904359654-1ya4bolhv",
      "x": 340.117949963089,
      "y": 97.49022491256714,
      "type": "standard"
    },
    {
      "id": "cone-1776904359654-0q6avyyg9",
      "x": 341.3251830758534,
      "y": 98.37702275294686,
      "type": "standard"
    },
    {
      "id": "cone-1776904359654-y168k5skp",
      "x": 342.04578966212273,
      "y": 99.69054630446436,
      "type": "standard"
    },
    {
      "id": "cone-1776904359654-shv50xusb",
      "x": 342.2445772262898,
      "y": 101.1776713044777,
      "type": "standard"
    },
    {
      "id": "cone-1776904359654-9nx303edw",
      "x": 342.20795148444176,
      "y": 102.69065951776506,
      "type": "standard"
    },
    {
      "id": "cone-1776904359654-xka786dwt",
      "x": 342.1210240254669,
      "y": 104.19213107441712,
      "type": "standard"
    },
    {
      "id": "cone-1776904384607-chjv1c6v2",
      "x": 217.44189453125,
      "y": 166.7815399169922,
      "type": "standard"
    },
    {
      "id": "cone-1776904386310-4g5vyfwn4",
      "x": 216.1580047607422,
      "y": 167.68026733398438,
      "type": "standard"
    },
    {
      "id": "cone-1776904387464-8cp3veeqt",
      "x": 214.74574279785156,
      "y": 168.5789794921875,
      "type": "standard"
    },
    {
      "id": "cone-1776904388424-wv17ves5w",
      "x": 213.205078125,
      "y": 169.47769165039062,
      "type": "standard"
    },
    {
      "id": "cone-1776904389902-30zkh8s0u",
      "x": 211.9211883544922,
      "y": 170.3764190673828,
      "type": "standard"
    },
    {
      "id": "cone-1776904399757-6bdt1siua",
      "x": 196.2578125,
      "y": 187.70884704589844,
      "type": "pointer",
      "rotation": 11
    },
    {
      "id": "cone-1776904399757-vif23sjay",
      "x": 193.7878419905901,
      "y": 187.23428104817867,
      "type": "pointer",
      "rotation": 12
    },
    {
      "id": "cone-1776904399757-2nbryshqh",
      "x": 191.35853293611146,
      "y": 186.53738262413788,
      "type": "pointer",
      "rotation": 20
    },
    {
      "id": "cone-1776904399757-pzrj41d8y",
      "x": 189.02698132324218,
      "y": 185.59402685546877,
      "type": "pointer",
      "rotation": 23
    },
    {
      "id": "cone-1776904399757-iowsd98uz",
      "x": 186.73069882714844,
      "y": 184.59193391796873,
      "type": "pointer",
      "rotation": 24
    },
    {
      "id": "cone-1776904408104-gen6h1bom",
      "x": 150.16639709472656,
      "y": 182.57330322265625,
      "type": "pointer",
      "rotation": 15
    },
    {
      "id": "cone-1776904408105-7nqr8ibnc",
      "x": 147.7451848932495,
      "y": 181.94017388400263,
      "type": "pointer",
      "rotation": 15
    },
    {
      "id": "cone-1776904408105-bcpqi7xmg",
      "x": 145.34767483654787,
      "y": 181.16513660131835,
      "type": "pointer",
      "rotation": 22
    },
    {
      "id": "cone-1776904408105-pws18lj61",
      "x": 143.08886228594972,
      "y": 180.02058781982421,
      "type": "pointer",
      "rotation": 30
    },
    {
      "id": "cone-1776904408105-ipaw0fd5w",
      "x": 140.936432341218,
      "y": 178.71706834793088,
      "type": "pointer",
      "rotation": 32
    },
    {
      "id": "cone-1776904421665-njv35exsy",
      "x": 196.34591674804688,
      "y": 132.50184631347656,
      "type": "standard"
    },
    {
      "id": "cone-1776904421665-zvlb3d76p",
      "x": 194.34701785087583,
      "y": 132.42350589561462,
      "type": "standard"
    },
    {
      "id": "cone-1776904421665-bfpo6ilio",
      "x": 192.3369081772919,
      "y": 132.35009318070988,
      "type": "standard"
    },
    {
      "id": "cone-1776904421665-01g4je3ru",
      "x": 190.32060303547667,
      "y": 132.28314772688293,
      "type": "standard"
    },
    {
      "id": "cone-1776904477520-u746joz73",
      "x": 138.71473693847656,
      "y": 162.22068786621094,
      "type": "standard"
    },
    {
      "id": "cone-1776904478187-z8e7pe9cr",
      "x": 140.06517028808594,
      "y": 163.5711212158203,
      "type": "standard"
    },
    {
      "id": "cone-1776904478899-s00juaods",
      "x": 141.2227020263672,
      "y": 165.30740356445312,
      "type": "standard"
    },
    {
      "id": "cone-1776904479455-2ytk43v5k",
      "x": 142.4766845703125,
      "y": 166.75430297851562,
      "type": "standard"
    },
    {
      "id": "cone-1776904492363-acqiibv7l",
      "x": 132.05899047851562,
      "y": 160.00210571289062,
      "type": "pointer",
      "rotation": 31
    },
    {
      "id": "cone-1776904492363-wlh86cmhy",
      "x": 129.49813692744684,
      "y": 158.43754984292983,
      "type": "pointer",
      "rotation": 28
    },
    {
      "id": "cone-1776904492363-lnb0rdyua",
      "x": 126.66634215551761,
      "y": 157.3767517774658,
      "type": "pointer",
      "rotation": 13
    },
    {
      "id": "cone-1776904492363-a6nnwd3i3",
      "x": 123.69839084529876,
      "y": 156.85166860389708,
      "type": "pointer",
      "rotation": 8
    },
    {
      "id": "cone-1776904492363-jca0973q0",
      "x": 120.71345270502472,
      "y": 156.45732231724548,
      "type": "pointer",
      "rotation": 7
    },
    {
      "id": "cone-1776904492363-2c29b1t7u",
      "x": 117.73151190332031,
      "y": 156.09390544299316,
      "type": "pointer",
      "rotation": 8
    },
    {
      "id": "cone-1776904499277-yh2szylau",
      "x": 131.88656616210938,
      "y": 165.78970336914062,
      "type": "pointer",
      "rotation": 134
    },
    {
      "id": "cone-1776904522198-qjy28g3jg",
      "x": 123.22148895263672,
      "y": 136.34774780273438,
      "type": "pointer",
      "rotation": 149
    },
    {
      "id": "cone-1776904522198-y4ow8kjnx",
      "x": 126.24778709932804,
      "y": 134.54613724607228,
      "type": "pointer",
      "rotation": 145
    },
    {
      "id": "cone-1776904522198-p5y2xhivt",
      "x": 128.65258120775223,
      "y": 132.01417077064514,
      "type": "pointer",
      "rotation": 123
    },
    {
      "id": "cone-1776904522198-vnzj0nfmf",
      "x": 130.34897785455703,
      "y": 128.93272857276915,
      "type": "pointer",
      "rotation": 117
    },
    {
      "id": "cone-1776904522198-s0dbgchgh",
      "x": 131.88910004400253,
      "y": 125.78481374305726,
      "type": "pointer",
      "rotation": 117
    },
    {
      "id": "cone-1776904536328-0ig67wat6",
      "x": 78.21755981445312,
      "y": 134.5877227783203,
      "type": "pointer",
      "rotation": 135
    },
    {
      "id": "cone-1776904536328-qw61gsjs5",
      "x": 80.34301223723222,
      "y": 132.4664729215927,
      "type": "pointer",
      "rotation": 136
    },
    {
      "id": "cone-1776904536328-gpmq12l1h",
      "x": 82.72358750732423,
      "y": 130.6368709277344,
      "type": "pointer",
      "rotation": 154
    },
    {
      "id": "cone-1776904536328-24lf5veya",
      "x": 85.61141375106811,
      "y": 129.80962874084474,
      "type": "pointer",
      "rotation": 169
    },
    {
      "id": "cone-1776904610962-nvkt082z8",
      "x": 120.5457992553711,
      "y": 105.79396057128906,
      "type": "standard"
    },
    {
      "id": "cone-1776904610962-mdoklfggh",
      "x": 121.37391033209659,
      "y": 102.88809694824171,
      "type": "standard"
    },
    {
      "id": "cone-1776904610962-rxj8rkaqw",
      "x": 123.24499717128278,
      "y": 100.52480528420212,
      "type": "standard"
    },
    {
      "id": "cone-1776904610962-lxnbexsst",
      "x": 125.54054581152344,
      "y": 98.54121772753908,
      "type": "standard"
    },
    {
      "id": "cone-1776904610962-2n8zcv0m1",
      "x": 128.00164938065814,
      "y": 96.74785031615878,
      "type": "standard"
    },
    {
      "id": "cone-1776904610963-syqy0kxmm",
      "x": 130.66946086328124,
      "y": 95.2548974140625,
      "type": "standard"
    },
    {
      "id": "cone-1776904610963-3yem6hwvs",
      "x": 133.5436003774414,
      "y": 94.23866193310546,
      "type": "standard"
    },
    {
      "id": "cone-1776904610963-b9yyn1whr",
      "x": 136.51352979687502,
      "y": 93.7038860263672,
      "type": "standard"
    },
    {
      "id": "cone-1776904610963-ud3k5jwzm",
      "x": 139.55794611777117,
      "y": 93.56829773643875,
      "type": "standard"
    },
    {
      "id": "cone-1776904610963-5vkrsdjuu",
      "x": 142.62932501531742,
      "y": 93.53685578662825,
      "type": "standard"
    },
    {
      "id": "cone-1776904610963-wb6xjjap0",
      "x": 145.680112562614,
      "y": 93.48892297130729,
      "type": "standard"
    },
    {
      "id": "cone-1776904610963-6x2h40wf3",
      "x": 148.83504333209987,
      "y": 93.40932113456724,
      "type": "standard"
    },
    {
      "id": "cone-1776904610963-mx11ja5uu",
      "x": 151.97634798895263,
      "y": 93.34551659875488,
      "type": "standard"
    },
    {
      "id": "cone-1776904610963-0lhl6x41q",
      "x": 154.988280494689,
      "y": 93.29628241190528,
      "type": "standard"
    },
    {
      "id": "cone-1776904610963-lb3l80izq",
      "x": 158.0453011942873,
      "y": 93.25344398446467,
      "type": "standard"
    },
    {
      "id": "cone-1776904610963-h7uttnmb6",
      "x": 161.2713360975523,
      "y": 93.21351004892158,
      "type": "standard"
    },
    {
      "id": "cone-1776904610963-a9he738li",
      "x": 164.3598872666626,
      "y": 93.17894247790527,
      "type": "standard"
    },
    {
      "id": "cone-1776904610963-hwy724vtu",
      "x": 167.4830878595934,
      "y": 93.14671422471427,
      "type": "standard"
    },
    {
      "id": "cone-1776904610963-n2jl5mle2",
      "x": 170.5874538488388,
      "y": 93.11674581336975,
      "type": "standard"
    },
    {
      "id": "cone-1776904610963-q5bq5h9tv",
      "x": 173.61950120689298,
      "y": 93.08895776789285,
      "type": "standard"
    },
    {
      "id": "cone-1776904610963-x63rwagzz",
      "x": 176.74255875036337,
      "y": 93.06137941735649,
      "type": "standard"
    },
    {
      "id": "cone-1776904610963-2rad1ezrx",
      "x": 179.85089325585938,
      "y": 93.03442221777343,
      "type": "standard"
    },
    {
      "id": "cone-1776904610963-z8hawpjp6",
      "x": 182.97475627328208,
      "y": 93.00696013250543,
      "type": "standard"
    },
    {
      "id": "cone-1776904610963-c0hv29fub",
      "x": 186.07686949062347,
      "y": 92.9773132724762,
      "type": "standard"
    },
    {
      "id": "cone-1776904624853-0tzh3sdvh",
      "x": 128.55198669433594,
      "y": 106.08334350585938,
      "type": "standard"
    },
    {
      "id": "cone-1776904624853-ej1p5ck3t",
      "x": 130.02757697413443,
      "y": 103.46262949191998,
      "type": "standard"
    },
    {
      "id": "cone-1776904624853-9881s0rdk",
      "x": 132.07454572872925,
      "y": 101.26732456187058,
      "type": "standard"
    },
    {
      "id": "cone-1776904624853-u7azo1cw7",
      "x": 134.71946930441283,
      "y": 99.81979139362717,
      "type": "standard"
    },
    {
      "id": "cone-1776904624853-iws0dd6fk",
      "x": 137.4197690761719,
      "y": 98.54665945019532,
      "type": "standard"
    },
    {
      "id": "cone-1776904624853-256ouzuwj",
      "x": 140.41022823047638,
      "y": 98.04813564127684,
      "type": "standard"
    },
    {
      "id": "cone-1776904624853-8l3xh6cui",
      "x": 143.51822506250767,
      "y": 97.8966819513507,
      "type": "standard"
    },
    {
      "id": "cone-1776904624853-h75ur28ns",
      "x": 146.58583162902073,
      "y": 97.81942902143861,
      "type": "standard"
    },
    {
      "id": "cone-1776904624853-0r5i60ots",
      "x": 149.60944225969698,
      "y": 97.77569312214662,
      "type": "standard"
    },
    {
      "id": "cone-1776904624853-1610shg9m",
      "x": 152.6412431230469,
      "y": 97.74679291601564,
      "type": "standard"
    },
    {
      "id": "cone-1776904624853-mbxf02f2g",
      "x": 155.706124255496,
      "y": 97.72678565504263,
      "type": "standard"
    },
    {
      "id": "cone-1776904624853-tb68zrpct",
      "x": 158.9459455154648,
      "y": 97.71245752552797,
      "type": "standard"
    },
    {
      "id": "cone-1776904624853-k5mrctpix",
      "x": 162.0366336514053,
      "y": 97.70351619975281,
      "type": "standard"
    },
    {
      "id": "cone-1776904624853-sr7565yfv",
      "x": 165.17181569060514,
      "y": 97.69798145857239,
      "type": "standard"
    },
    {
      "id": "cone-1776904624853-mryajsyqc",
      "x": 168.3012992296219,
      "y": 97.69516573143007,
      "type": "standard"
    },
    {
      "id": "cone-1776904624853-4l67259s9",
      "x": 171.37489186501313,
      "y": 97.69438144776916,
      "type": "standard"
    },
    {
      "id": "cone-1776904624853-i2ugp11ff",
      "x": 174.5833318010569,
      "y": 97.69502677750587,
      "type": "standard"
    },
    {
      "id": "cone-1776904624853-9ppqdwvji",
      "x": 177.60345596331788,
      "y": 97.69637510595703,
      "type": "standard"
    },
    {
      "id": "cone-1776904624853-k073r685x",
      "x": 180.77084922256188,
      "y": 97.69766244632149,
      "type": "standard"
    },
    {
      "id": "cone-1776904624853-az68ebxrs",
      "x": 183.15577132415774,
      "y": 97.69715032958985,
      "type": "standard"
    },
    {
      "id": "cone-1776904650789-vvr9yiusp",
      "x": 174.3705291748047,
      "y": 110.90634155273438,
      "type": "standard"
    },
    {
      "id": "cone-1776904650789-9o4kwo52e",
      "x": 174.87900569015505,
      "y": 108.44143908920432,
      "type": "standard"
    },
    {
      "id": "cone-1776904650789-o7p9bh3nf",
      "x": 175.5508912394714,
      "y": 106.01514569952535,
      "type": "standard"
    },
    {
      "id": "cone-1776904650789-px2j2aqjm",
      "x": 176.78478158376123,
      "y": 103.84446872938014,
      "type": "standard"
    },
    {
      "id": "cone-1776904650789-o32p0gjes",
      "x": 178.59094950303648,
      "y": 102.08854966350938,
      "type": "standard"
    },
    {
      "id": "cone-1776904650789-up35hij0h",
      "x": 180.58158507752418,
      "y": 100.564149759233,
      "type": "standard"
    },
    {
      "id": "cone-1776904650789-8tjrbiian",
      "x": 182.63992299511716,
      "y": 99.12722749972534,
      "type": "standard"
    },
    {
      "id": "cone-1776904650789-4twkc2zjv",
      "x": 184.76458856706236,
      "y": 97.78836838038252,
      "type": "standard"
    },
    {
      "id": "cone-1776904650789-50i4w7gwd",
      "x": 186.98773714894105,
      "y": 96.62667270363235,
      "type": "standard"
    },
    {
      "id": "cone-1776904650789-lqnixo9k2",
      "x": 189.2401874281712,
      "y": 95.54239510184051,
      "type": "standard"
    },
    {
      "id": "cone-1776904650789-kk5cw02vr",
      "x": 191.594678491354,
      "y": 94.66836006194353,
      "type": "standard"
    },
    {
      "id": "cone-1776904650789-g00p58gp1",
      "x": 193.52890988419819,
      "y": 92.77974392182398,
      "type": "standard"
    },
    {
      "id": "cone-1776904650789-rmmr78o9o",
      "x": 193.97211200370026,
      "y": 90.46360909647751,
      "type": "standard"
    },
    {
      "id": "cone-1776904650789-msnudk3nu",
      "x": 193.99127368164062,
      "y": 88.45352154541015,
      "type": "standard"
    }
  ],
  "startMarker": {
    "x": 177.21604919433594,
    "y": 119.02106475830078,
    "rotation": 177
  },
  "timingStartMarker": {
    "x": 203.9208221435547,
    "y": 129.54891204833984,
    "rotation": 122
  },
  "finishMarker": {
    "x": 125.05940246582031,
    "y": 115.64401245117188,
    "rotation": 356
  },
  "carMarker": null,
  "cornerNumbers": [
    {
      "id": "corner-1776904698603-723wjjyz3",
      "x": 268.6451416015625,
      "y": 82.24280548095703,
      "number": 1
    },
    {
      "id": "corner-1776904700045-i4cog9kfw",
      "x": 303.5010070800781,
      "y": 152.40577697753906,
      "number": 2
    },
    {
      "id": "corner-1776904701672-kwl6zo4ac",
      "x": 209.0387420654297,
      "y": 156.7310333251953,
      "number": 3
    },
    {
      "id": "corner-1776904702931-lys8rrdrx",
      "x": 145.8608856201172,
      "y": 136.73440551757812,
      "number": 4
    }
  ],
  "drivingLine": [],
  "createdAt": "2026-04-06T03:17:32.856Z",
  "updatedAt": "2026-04-06T03:17:32.856Z"
}